audit_tools/__init__.py
audit_tools/auto_fix.py
audit_tools/auto_fix_semantics.py
audit_tools/cli_input.py
audit_tools/invariants_check.py
audit_tools/parse_ast.py
audit_tools/parse_slither.py
solcheck-0.1.5.dist-info/licenses/LICENSE
solcheck-0.1.5.dist-info/METADATA
solcheck-0.1.5.dist-info/WHEEL
solcheck-0.1.5.dist-info/top_level.txt
solcheck-0.1.5.dist-info/RECORD
