Metadata-Version: 2.4
Name: solcheck
Version: 0.1.5
Summary: A smart contract auditing tools
Home-page: https://github.com/faizqowy/solcheck
Author: Faiz Qowy
Author-email: faizislamicqowy@gmail.com
Classifier: Programming Language :: Python :: 3
Classifier: License :: OSI Approved :: MIT License
Classifier: Operating System :: OS Independent
Requires-Python: >=3.7
License-File: LICENSE
Requires-Dist: slither-analyzer
Requires-Dist: py-solc-x
Dynamic: author
Dynamic: author-email
Dynamic: classifier
Dynamic: description
Dynamic: description-content-type
Dynamic: home-page
Dynamic: license-file
Dynamic: requires-dist
Dynamic: requires-python
Dynamic: summary
